pyeloverblik/__init__.py
pyeloverblik/__main__.py
pyeloverblik/eloverblik.py
pyeloverblik/models.py
pyeloverblik-0.4.4.dist-info/LICENSE
pyeloverblik-0.4.4.dist-info/METADATA
pyeloverblik-0.4.4.dist-info/WHEEL
pyeloverblik-0.4.4.dist-info/top_level.txt
pyeloverblik-0.4.4.dist-info/RECORD
