Metadata-Version: 2.2
Name: pyeloverblik
Version: 0.4.4
Summary: Python wrapper for eloverblik.dk API.
Home-page: https://github.com/JonasPed/pyeloverblik
Author: Jonas Pedersen
Author-email: jonas@pedersen.ninja
License: Apache 2.0
License-File: LICENSE
Requires-Dist: requests>=2.32.3
Dynamic: author
Dynamic: author-email
Dynamic: description
Dynamic: description-content-type
Dynamic: home-page
Dynamic: license
Dynamic: requires-dist
Dynamic: summary
